[
    {
        "id": "POND-0001",
        "name": "A1",
        "color": "#2196F3",
        "geometry": {
            "type": "Feature",
            "properties": {},
            "geometry": {
                "type": "Polygon",
                "coordinates": [
                    [
                        [
                            -109.390655,
                            26.005997
                        ],
                        [
                            -109.387908,
                            26.004917
                        ],
                        [
                            -109.390483,
                            25.999787
                        ],
                        [
                            -109.393101,
                            26.001137
                        ],
                        [
                            -109.390655,
                            26.005997
                        ]
                    ]
                ]
            }
        },
        "metrics": {
            "area": 0,
            "perimeter": 0
        },
        "feeders": [],
        "createdAt": "2026-07-05T03:11:54.550Z",
        "updatedAt": "2026-07-05T03:11:54.550Z"
    }
]